PygameHaze/__init__.py
PygameHaze/constants.py
PygameHaze/exceptions.py
PygameHaze/types.py
PygameHaze/Classes/__init__.py
PygameHaze/Classes/animation.py
PygameHaze/Classes/button.py
PygameHaze/Classes/cloth.py
PygameHaze/Classes/font.py
PygameHaze/Classes/input_field.py
PygameHaze/Classes/managers.py
PygameHaze/Classes/particle.py
PygameHaze/Classes/quadtree.py
PygameHaze/Classes/spritesheet.py
PygameHaze/Classes/text.py
PygameHaze/utils/__init__.py
PygameHaze/utils/_numba_utils.py
PygameHaze/utils/draw.py
PygameHaze/utils/formulas.py
PygameHaze/utils/noise.py
PygameHaze/utils/pathfinding.py
PygameHaze/utils/surface.py
PygameHaze/utils/utils.py
PygameHaze-0.3.6.dist-info/LICENSE
PygameHaze-0.3.6.dist-info/METADATA
PygameHaze-0.3.6.dist-info/WHEEL
PygameHaze-0.3.6.dist-info/top_level.txt
PygameHaze-0.3.6.dist-info/RECORD
