Metadata-Version: 2.1
Name: PygameHaze
Version: 0.3.6
Summary: helpful tools/widgets for pygame
Home-page: https://github.com/Emc2356/PygameHaze
Author: emc235
Author-email: emc235.dev@gmail.com
License: MIT
Platform: UNKNOWN
Requires-Python: >=3.7
License-File: LICENSE
Requires-Dist: pygame (~=2.1.0)
Requires-Dist: numpy (~=1.20.3)
